res_lpf_fix.v
// can you write from scratch a resonant low pass filter in verilog with signed input of 16bit ?

// note output is a reserved keyword, and cannot be used as a register name

// add a reset signal, active low

// add $signed to both sides of comparisons, and right side of assignments

module ResonantLowPassFilter(
    input clk,
    input signed [15:0] audio_in,
    input signed [15:0] cutoff,
    input signed [15:0] resonance,
    input signed [15:0] gain,
    input reset_n,
    output reg signed [15:0] filtered_audio
);

    // Constants
    parameter [15:0] MAX_POS_VALUE = 16'h7FFF;
    parameter [15:0] MIN_NEG_VALUE = -16'h8000;

    // Internal registers
    reg signed [15:0] state;
    reg signed [15:0] feedback;
    reg signed [15:0] output_reg;

    always @(posedge clk or negedge reset_n) begin
        if (!reset_n) begin
            state <= $signed(16'h0000);
            feedback <= $signed(16'h0000);
            output_reg <= $signed(16'h0000);
        end else begin
            // Calculate feedback signal and limit it to the output range
            feedback <= $signed((state * resonance) >> 15);
            if (feedback > $signed(MAX_POS_VALUE))
                feedback <= MAX_POS_VALUE;
            else if (feedback < $signed(MIN_NEG_VALUE))
                feedback <= $signed(MIN_NEG_VALUE);

            // Update state and filtered_audio
            state <= $signed(audio_in - feedback);
            output_reg <= $signed((state * cutoff) >> 15);
            filtered_audio <= $signed((output_reg + gain) >> 1); // Apply gain and round off
        end
    end

endmodule

res_lpf.vcd
$version Generated by VerilatedVcd $end
$date Sat Jul 29 22:35:12 2023
 $end
$timescale   1ps $end

 $scope module TOP $end
  $var wire 16 ' audio_in [15:0] $end
  $var wire  1 & clk $end
  $var wire 16 ( cutoff [15:0] $end
  $var wire 16 , filtered_audio [15:0] $end
  $var wire 16 * gain [15:0] $end
  $var wire  1 + reset_n $end
  $var wire 16 ) resonance [15:0] $end
  $scope module ResonantLowPassFilter $end
   $var wire 16 - MAX_POS_VALUE [15:0] $end
   $var wire 16 . MIN_NEG_VALUE [15:0] $end
   $var wire 16 ' audio_in [15:0] $end
   $var wire  1 & clk $end
   $var wire 16 ( cutoff [15:0] $end
   $var wire 16 $ feedback [15:0] $end
   $var wire 16 , filtered_audio [15:0] $end
   $var wire 16 * gain [15:0] $end
   $var wire 16 % output_reg [15:0] $end
   $var wire  1 + reset_n $end
   $var wire 16 ) resonance [15:0] $end
   $var wire 16 # state [15:0] $end
  $upscope $end
 $upscope $end
$enddefinitions $end


#5
b0000000000000000 #
b0000000000000000 $
b0000000000000000 %
0&
b0000000000000000 '
b0000000000000000 (
b0000000000000000 )
b0000000000000000 *
0+
b0000000000000000 ,
b0111111111111111 -
b1000000000000000 .
#10
#15
1&
1+
#20
#25
0&
#30
#35
b0000000000100000 #
1&
b0000000000100000 '
b0000000010000000 (
b0111000000000000 )
#40
#45
0&
#50
#55
1&
#60
#65
0&
#70
#75
1&
#80
#85
0&
#90
#95
1&
#100
#105
0&
#110
#115
1&
#120
#125
0&
#130
#135
1&
#140
#145
0&
#150
#155
1&
#160
#165
0&
#170
#175
1&
#180
#185
0&
#190
#195
1&
#200
#205
0&
#210
#215
1&
#220
#225
0&
#230
#235
1&
#240
#245
0&
#250
#255
1&
#260
#265
0&
#270
#275
1&
#280
#285
0&
#290
#295
1&
#300
#305
0&
#310
#315
1&
#320
#325
0&
#330
#335
1&
#340
#345
0&
#350
#355
1&
#360
#365
0&
#370
#375
1&
#380
#385
0&
#390
#395
1&
#400
#405
0&
#410
#415
1&
#420
#425
0&
#430
#435
1&
#440
#445
0&
#450
#455
1&
#460
#465
0&
#470
#475
1&
#480
#485
0&
#490
#495
1&
#500
#505
0&
#510
#515
1&
#520
#525
0&
#530
#535
1&
#540
#545
0&
#550
#555
1&
#560
#565
0&
#570
#575
1&
#580
#585
0&
#590
#595
1&
#600
#605
0&
#610
#615
1&
#620
#625
0&
#630
#635
1&
#640
#645
0&
#650
#655
1&
#660
#665
0&
#670
#675
1&
#680
#685
0&
#690
#695
1&
#700
#705
0&
#710
#715
1&
#720
#725
0&
#730
#735
1&
#740
#745
0&
#750
#755
1&
#760
#765
0&
#770
#775
1&
#780
#785
0&
#790
#795
1&
#800
#805
0&
#810
#815
1&
#820
#825
0&
#830
#835
1&
#840
#845
0&
#850
#855
1&
#860
#865
0&
#870
#875
1&
#880
#885
0&
#890
#895
1&
#900
#905
0&
#910
#915
1&
#920
#925
0&
#930
#935
1&
#940
#945
0&
#950
#955
1&
#960
#965
0&
#970
#975
1&
#980
#985
0&
#990
#995
1&
#1000
#1005
0&
#1010
#1015
1&
#1020
#1025
0&
#1030
#1035
b1111111111100000 #
1&
b1111111111100000 '
#1040
#1045
0&
#1050
#1055
b0000000000000001 %
1&
#1060
#1065
0&
#1070
#1075
1&
#1080
#1085
0&
#1090
#1095
1&
#1100
#1105
0&
#1110
#1115
1&
#1120
#1125
0&
#1130
#1135
1&
#1140
#1145
0&
#1150
#1155
1&
#1160
#1165
0&
#1170
#1175
1&
#1180
#1185
0&
#1190
#1195
1&
#1200
#1205
0&
#1210
#1215
1&
#1220
#1225
0&
#1230
#1235
1&
#1240
#1245
0&
#1250
#1255
1&
#1260
#1265
0&
#1270
#1275
1&
#1280
#1285
0&
#1290
#1295
1&
#1300
#1305
0&
#1310
#1315
1&
#1320
#1325
0&
#1330
#1335
1&
#1340
#1345
0&
#1350
#1355
1&
#1360
#1365
0&
#1370
#1375
1&
#1380
#1385
0&
#1390
#1395
1&
#1400
#1405
0&
#1410
#1415
1&
#1420
#1425
0&
#1430
#1435
1&
#1440
#1445
0&
#1450
#1455
1&
#1460
#1465
0&
#1470
#1475
1&
#1480
#1485
0&
#1490
#1495
1&
#1500
#1505
0&
#1510
#1515
1&
#1520
#1525
0&
#1530
#1535
1&
#1540
#1545
0&
#1550
#1555
1&
#1560
#1565
0&
#1570
#1575
1&
#1580
#1585
0&
#1590
#1595
1&
#1600
#1605
0&
#1610
#1615
1&
#1620
#1625
0&
#1630
#1635
1&
#1640
#1645
0&
#1650
#1655
1&
#1660
#1665
0&
#1670
#1675
1&
#1680
#1685
0&
#1690
#1695
1&
#1700
#1705
0&
#1710
#1715
1&
#1720
#1725
0&
#1730
#1735
1&
#1740
#1745
0&
#1750
#1755
1&
#1760
#1765
0&
#1770
#1775
1&
#1780
#1785
0&
#1790
#1795
1&
#1800
#1805
0&
#1810
#1815
1&
#1820
#1825
0&
#1830
#1835
1&
#1840
#1845
0&
#1850
#1855
1&
#1860
#1865
0&
#1870
#1875
1&
#1880
#1885
0&
#1890
#1895
1&
#1900
#1905
0&
#1910
#1915
1&
#1920
#1925
0&
#1930
#1935
1&
#1940
#1945
0&
#1950
#1955
1&
#1960
#1965
0&
#1970
#1975
1&
#1980
#1985
0&
#1990
#1995
1&
#2000
#2005
0&
#2010
#2015
1&
#2020
#2025
0&
#2030
#2035
b0000000000100000 #
1&
b0000000000100000 '
#2040
#2045
0&
#2050
#2055
b0000000000000000 %
1&
#2060
#2065
0&
#2070
#2075
1&
#2080
#2085
0&
#2090
#2095
1&
#2100
#2105
0&
#2110
#2115
1&
#2120
#2125
0&
#2130
#2135
1&
#2140
#2145
0&
#2150
#2155
1&
#2160
#2165
0&
#2170
#2175
1&
#2180
#2185
0&
#2190
#2195
1&
#2200
#2205
0&
#2210
#2215
1&
#2220
#2225
0&
#2230
#2235
1&
#2240
#2245
0&
#2250
#2255
1&
#2260
#2265
0&
#2270
#2275
1&
#2280
#2285
0&
#2290
#2295
1&
#2300
#2305
0&
#2310
#2315
1&
#2320
#2325
0&
#2330
#2335
1&
#2340
#2345
0&
#2350
#2355
1&
#2360
#2365
0&
#2370
#2375
1&
#2380
#2385
0&
#2390
#2395
1&
#2400
#2405
0&
#2410
#2415
1&
#2420
#2425
0&
#2430
#2435
1&
#2440
#2445
0&
#2450
#2455
1&
#2460
#2465
0&
#2470
#2475
1&
#2480
#2485
0&
#2490
#2495
1&
#2500
#2505
0&
#2510
#2515
1&
#2520
#2525
0&
#2530
#2535
1&
#2540
#2545
0&
#2550
#2555
1&
#2560
#2565
0&
#2570
#2575
1&
#2580
#2585
0&
#2590
#2595
1&
#2600
#2605
0&
#2610
#2615
1&
#2620
#2625
0&
#2630
#2635
1&
#2640
#2645
0&
#2650
#2655
1&
#2660
#2665
0&
#2670
#2675
1&
#2680
#2685
0&
#2690
#2695
1&
#2700
#2705
0&
#2710
#2715
1&
#2720
#2725
0&
#2730
#2735
1&
#2740
#2745
0&
#2750
#2755
1&
#2760
#2765
0&
#2770
#2775
1&
#2780
#2785
0&
#2790
#2795
1&
#2800
#2805
0&
#2810
#2815
1&
#2820
#2825
0&
#2830
#2835
1&
#2840
#2845
0&
#2850
#2855
1&
#2860
#2865
0&
#2870
#2875
1&
#2880
#2885
0&
#2890
#2895
1&
#2900
#2905
0&
#2910
#2915
1&
#2920
#2925
0&
#2930
#2935
1&
#2940
#2945
0&
#2950
#2955
1&
#2960
#2965
0&
#2970
#2975
1&
#2980
#2985
0&
#2990
#2995
1&
#3000
#3005
0&
#3010
#3015
1&
#3020
#3025
0&
#3030
#3035
b1111111111100000 #
1&
b1111111111100000 '
#3040
#3045
0&
#3050
#3055
b0000000000000001 %
1&
